Metadata-Version: 2.1
Name: nllb-serve
Version: 0.2.1
Summary: NLLB Serve
Home-page: https://github.com/thammegowda/nllb-serve
Author: Thamme Gowda
Author-email: tgowdan@gmail.com
License: Apache
Classifier: Programming Language :: Python :: 3
Classifier: Programming Language :: Python :: 3.8
Classifier: Programming Language :: Python :: 3.9
Classifier: Programming Language :: Python :: 3.10
Classifier: Programming Language :: Python :: 3.11
Classifier: Programming Language :: Python :: 3.12
Classifier: License :: OSI Approved :: MIT License
Classifier: Topic :: Scientific/Engineering :: Artificial Intelligence
Requires-Python: >=3.8
Requires-Dist: transformers >=4.21
Requires-Dist: Flask ==3.0.2
Requires-Dist: Werkzeug >=3.0.0
Requires-Dist: torch >=1.12
Requires-Dist: gunicorn
Requires-Dist: gevent
Requires-Dist: sentence-splitter
